MANIFEST.in
VERSION
setup.py
canonical.ext.bittensor.egg-info/PKG-INFO
canonical.ext.bittensor.egg-info/SOURCES.txt
canonical.ext.bittensor.egg-info/dependency_links.txt
canonical.ext.bittensor.egg-info/requires.txt
canonical.ext.bittensor.egg-info/top_level.txt
canonical/ext/bittensor/__init__.py
canonical/ext/bittensor/_const.py
canonical/ext/bittensor/_environment.py
canonical/ext/bittensor/_metagraph.py
canonical/ext/bittensor/_miner.py
canonical/ext/bittensor/_validator.py
canonical/ext/bittensor/package.json
canonical/ext/bittensor/axon/__init__.py
canonical/ext/bittensor/axon/_apiroute.py
canonical/ext/bittensor/axon/_axon.py
canonical/ext/bittensor/axon/_request.py
canonical/ext/bittensor/axon/_response.py
canonical/ext/bittensor/axon/_router.py
canonical/ext/bittensor/bases/__init__.py
canonical/ext/bittensor/bases/_soma.py
canonical/ext/bittensor/datasets/__init__.py
canonical/ext/bittensor/datasets/_persistedsynapse.py
canonical/ext/bittensor/models/__init__.py
canonical/ext/bittensor/models/_coldkeyref.py
canonical/ext/bittensor/models/_hotkey.py
canonical/ext/bittensor/models/_hotkeyprivatekey.py
canonical/ext/bittensor/models/_hotkeypublickey.py
canonical/ext/bittensor/models/_hotkeyref.py
canonical/ext/bittensor/models/_hotkeyset.py
canonical/ext/bittensor/models/_neuron.py
canonical/ext/bittensor/models/_neuronlist.py
canonical/ext/bittensor/models/_persistedsynapse.py
canonical/ext/bittensor/models/_synapseenvelope.py
canonical/ext/bittensor/models/_synapseheader.py
canonical/ext/bittensor/params/__init__.py
canonical/ext/bittensor/params/_runningtask.py
canonical/ext/bittensor/soma/__init__.py
canonical/ext/bittensor/soma/_axontransport.py
canonical/ext/bittensor/soma/_monitor.py
canonical/ext/bittensor/soma/_soma.py
canonical/ext/bittensor/soma/_task.py
canonical/ext/bittensor/soma/_taskrunner.py
canonical/ext/bittensor/types/__init__.py
canonical/ext/bittensor/types/_ss58address.py